chemparse/__init__.py
chemparse/__init__.pyi
chemparse/exceptions.py
chemparse/exceptions.pyi
chemparse/fun.py
chemparse/fun.pyi
chemparse-0.3.1.dist-info/LICENSE.txt
chemparse-0.3.1.dist-info/METADATA
chemparse-0.3.1.dist-info/WHEEL
chemparse-0.3.1.dist-info/top_level.txt
chemparse-0.3.1.dist-info/RECORD
