Metadata-Version: 2.1
Name: chemparse
Version: 0.3.1
Summary: Chemical formula parser
Author: Grayson Boyer, Victor Ignatenko
Author-email: gmboyer@asu.edu, vityaig@yandex.ru
Classifier: Programming Language :: Python :: 3
Classifier: License :: OSI Approved :: MIT License
Classifier: Operating System :: OS Independent
Requires-Python: >=3.6
License-File: LICENSE.txt
